LICENSE
MANIFEST.in
README.md
requirements.txt
setup.py
mini_lightning/__init__.py
mini_lightning/_mini_lightning.py
mini_lightning/_types.py
mini_lightning/_utils.py
mini_lightning/_visualize.py
mini_lightning/_warmup_lrs.py
mini_lightning.egg-info/PKG-INFO
mini_lightning.egg-info/SOURCES.txt
mini_lightning.egg-info/dependency_links.txt
mini_lightning.egg-info/requires.txt
mini_lightning.egg-info/top_level.txt
tests/test_mini_lightning.py
tests/test_select_device.py
tests/test_url.py
tests/test_utils.py
tests/test_visualize.py