Metadata-Version: 2.1
Name: mini-lightning
Version: 0.2.2
Summary: Mini-Lightning is a lightweight machine learning training library, which is a mini version of Pytorch-Lightning with only 1k lines of code. It has the advantages of faster, more concise and more flexible.
Home-page: https://github.com/ustcml/mini-lightning/
Author: Jintao Huang
Author-email: huangjintao@mail.ustc.edu.cn
License: MIT
Classifier: License :: OSI Approved :: MIT License
Classifier: Operating System :: OS Independent
Classifier: Programming Language :: Python
Classifier: Programming Language :: Python :: 3
Classifier: Programming Language :: Python :: 3.8
Classifier: Programming Language :: Python :: 3.9
Classifier: Programming Language :: Python :: 3.10
Requires-Python: >=3.8
License-File: LICENSE
